{
  "count": 267,
  "uniques": 33,
  "views": [
    {
      "timestamp": "2021-10-11T00:00:00Z",
      "count": 23,
      "uniques": 5
    },
    {
      "timestamp": "2021-10-12T00:00:00Z",
      "count": 58,
      "uniques": 6
    },
    {
      "timestamp": "2021-10-13T00:00:00Z",
      "count": 24,
      "uniques": 4
    },
    {
      "timestamp": "2021-10-14T00:00:00Z",
      "count": 45,
      "uniques": 5
    },
    {
      "timestamp": "2021-10-15T00:00:00Z",
      "count": 54,
      "uniques": 6
    },
    {
      "timestamp": "2021-10-16T00:00:00Z",
      "count": 31,
      "uniques": 3
    },
    {
      "timestamp": "2021-10-17T00:00:00Z",
      "count": 32,
      "uniques": 4
    }
  ]
}