[
  {
    "referrer": "github.com",
    "count": 316,
    "uniques": 48
  },
  {
    "referrer": "Google",
    "count": 98,
    "uniques": 23
  },
  {
    "referrer": "hf.space",
    "count": 96,
    "uniques": 21
  },
  {
    "referrer": "huggingface.co",
    "count": 80,
    "uniques": 22
  },
  {
    "referrer": "medium.com",
    "count": 25,
    "uniques": 6
  },
  {
    "referrer": "paperswithcode.com",
    "count": 16,
    "uniques": 2
  },
  {
    "referrer": "colab.research.google.com",
    "count": 10,
    "uniques": 2
  },
  {
    "referrer": "5ino87fs1tj-496ff2e9c6d22116-0-colab.googleusercontent.com",
    "count": 6,
    "uniques": 1
  },
  {
    "referrer": "cn.bing.com",
    "count": 3,
    "uniques": 3
  },
  {
    "referrer": "synthesio.atlassian.net",
    "count": 3,
    "uniques": 1
  }
]