[
  {
    "referrer": "Google",
    "count": 363,
    "uniques": 22
  },
  {
    "referrer": "pyabsa.readthedocs.io",
    "count": 362,
    "uniques": 15
  },
  {
    "referrer": "github.com",
    "count": 265,
    "uniques": 32
  },
  {
    "referrer": "huggingface.co",
    "count": 139,
    "uniques": 22
  },
  {
    "referrer": "yangheng-pyabsa.hf.space",
    "count": 105,
    "uniques": 12
  },
  {
    "referrer": "medium.com",
    "count": 87,
    "uniques": 16
  },
  {
    "referrer": "pypi.org",
    "count": 69,
    "uniques": 1
  },
  {
    "referrer": "notebooks.githubusercontent.com",
    "count": 41,
    "uniques": 2
  },
  {
    "referrer": "cn.bing.com",
    "count": 31,
    "uniques": 1
  },
  {
    "referrer": "Bing",
    "count": 23,
    "uniques": 2
  }
]