{
  "count": 632,
  "uniques": 68,
  "views": [
    {
      "timestamp": "2021-10-26T00:00:00Z",
      "count": 220,
      "uniques": 15
    },
    {
      "timestamp": "2021-10-27T00:00:00Z",
      "count": 96,
      "uniques": 10
    },
    {
      "timestamp": "2021-10-28T00:00:00Z",
      "count": 84,
      "uniques": 11
    },
    {
      "timestamp": "2021-10-29T00:00:00Z",
      "count": 55,
      "uniques": 8
    },
    {
      "timestamp": "2021-10-30T00:00:00Z",
      "count": 59,
      "uniques": 8
    },
    {
      "timestamp": "2021-10-31T00:00:00Z",
      "count": 42,
      "uniques": 8
    },
    {
      "timestamp": "2021-11-01T00:00:00Z",
      "count": 76,
      "uniques": 8
    }
  ]
}