[
  {
    "path": "/yangheng95/ABSADatasets",
    "title": "yangheng95/ABSADatasets: Public & Community-shared datasets for Aspect-based ...",
    "count": 555,
    "uniques": 114
  },
  {
    "path": "/yangheng95/ABSADatasets/tree/v1.2/datasets",
    "title": "yangheng95/ABSADatasets: Public & Community-shared datasets for Aspect-based ...",
    "count": 200,
    "uniques": 53
  },
  {
    "path": "/yangheng95/ABSADatasets/tree/v1.2/datasets/apc_datasets",
    "title": "ABSADatasets/yelp.train.txt at v1.2 · yangheng95/ABSADatasets",
    "count": 173,
    "uniques": 34
  },
  {
    "path": "/yangheng95/ABSADatasets/tree/v1.2/DPT",
    "title": "yangheng95/ABSADatasets: Public & Community-shared datasets for Aspect-based ...",
    "count": 113,
    "uniques": 43
  },
  {
    "path": "/yangheng95/ABSADatasets/tree/v1.2/datasets/atepc_datasets",
    "title": "ABSADatasets/train.xml.dat.atepc at v1.2 · yangheng95/ABSADatasets",
    "count": 112,
    "uniques": 29
  },
  {
    "path": "/yangheng95/ABSADatasets/tree/v1.2/datasets/apc_datasets/100.CustomDataset",
    "title": "ABSADatasets/datasets/apc_datasets at v1.2 · yangheng95/ABSADatasets · GitHub",
    "count": 79,
    "uniques": 23
  },
  {
    "path": "/yangheng95/ABSADatasets/tree/v1.2/datasets/text_classification",
    "title": "ABSADatasets/datasets/text_classification at v1.2 · yangheng95/ABSADatasets ·...",
    "count": 71,
    "uniques": 29
  },
  {
    "path": "/yangheng95/ABSADatasets/blob/v1.2/DPT/ABSADatasetPrepareTool.html",
    "title": "ABSADatasets/DPT at v1.2 · yangheng95/ABSADatasets",
    "count": 45,
    "uniques": 16
  },
  {
    "path": "/yangheng95/ABSADatasets/issues",
    "title": "yangheng95/ABSADatasets: Public & Community-shared datasets for Aspect-based ...",
    "count": 42,
    "uniques": 14
  },
  {
    "path": "/yangheng95/ABSADatasets/tree/v1.2/datasets/apc_datasets/101.ACL_Twitter/acl-14-short-data",
    "title": "ABSADatasets/datasets/apc_datasets at v1.2 · yangheng95/ABSADatasets · GitHub",
    "count": 31,
    "uniques": 13
  }
]