{
  "count": 1378,
  "uniques": 141,
  "views": [
    {
      "timestamp": "2023-11-24T00:00:00Z",
      "count": 143,
      "uniques": 17
    },
    {
      "timestamp": "2023-11-25T00:00:00Z",
      "count": 135,
      "uniques": 17
    },
    {
      "timestamp": "2023-11-26T00:00:00Z",
      "count": 155,
      "uniques": 16
    },
    {
      "timestamp": "2023-11-27T00:00:00Z",
      "count": 193,
      "uniques": 22
    },
    {
      "timestamp": "2023-11-28T00:00:00Z",
      "count": 221,
      "uniques": 28
    },
    {
      "timestamp": "2023-11-29T00:00:00Z",
      "count": 264,
      "uniques": 19
    },
    {
      "timestamp": "2023-11-30T00:00:00Z",
      "count": 267,
      "uniques": 22
    }
  ]
}