{
  "count": 545,
  "uniques": 107,
  "views": [
    {
      "timestamp": "2022-12-19T00:00:00Z",
      "count": 60,
      "uniques": 21
    },
    {
      "timestamp": "2022-12-20T00:00:00Z",
      "count": 98,
      "uniques": 19
    },
    {
      "timestamp": "2022-12-21T00:00:00Z",
      "count": 61,
      "uniques": 16
    },
    {
      "timestamp": "2022-12-22T00:00:00Z",
      "count": 90,
      "uniques": 18
    },
    {
      "timestamp": "2022-12-23T00:00:00Z",
      "count": 89,
      "uniques": 12
    },
    {
      "timestamp": "2022-12-24T00:00:00Z",
      "count": 50,
      "uniques": 9
    },
    {
      "timestamp": "2022-12-25T00:00:00Z",
      "count": 97,
      "uniques": 12
    }
  ]
}