{
  "count": 1103,
  "uniques": 214,
  "views": [
    {
      "timestamp": "2023-03-13T00:00:00Z",
      "count": 126,
      "uniques": 31
    },
    {
      "timestamp": "2023-03-14T00:00:00Z",
      "count": 226,
      "uniques": 39
    },
    {
      "timestamp": "2023-03-15T00:00:00Z",
      "count": 172,
      "uniques": 35
    },
    {
      "timestamp": "2023-03-16T00:00:00Z",
      "count": 147,
      "uniques": 32
    },
    {
      "timestamp": "2023-03-17T00:00:00Z",
      "count": 169,
      "uniques": 36
    },
    {
      "timestamp": "2023-03-18T00:00:00Z",
      "count": 117,
      "uniques": 22
    },
    {
      "timestamp": "2023-03-19T00:00:00Z",
      "count": 146,
      "uniques": 19
    }
  ]
}