[
  {
    "referrer": "github.com",
    "count": 883,
    "uniques": 84
  },
  {
    "referrer": "Google",
    "count": 65,
    "uniques": 5
  },
  {
    "referrer": "pypi.org",
    "count": 20,
    "uniques": 1
  },
  {
    "referrer": "gvyhx13wr5-496ff2e9c6d22116-0-colab.googleusercontent.com",
    "count": 9,
    "uniques": 2
  },
  {
    "referrer": "huggingface.co",
    "count": 7,
    "uniques": 5
  },
  {
    "referrer": "colab.research.google.com",
    "count": 5,
    "uniques": 5
  },
  {
    "referrer": "q1mlaujdgl-496ff2e9c6d22116-0-colab.googleusercontent.com",
    "count": 3,
    "uniques": 1
  },
  {
    "referrer": "qnzh0wv41e-496ff2e9c6d22116-0-colab.googleusercontent.com",
    "count": 1,
    "uniques": 1
  },
  {
    "referrer": "pwnymbs1i8f-496ff2e9c6d22116-0-colab.googleusercontent.com",
    "count": 1,
    "uniques": 1
  }
]