[
  {
    "referrer": "github.com",
    "count": 417,
    "uniques": 26
  },
  {
    "referrer": "huggingface.co",
    "count": 209,
    "uniques": 33
  },
  {
    "referrer": "medium.com",
    "count": 188,
    "uniques": 27
  },
  {
    "referrer": "pyabsa.readthedocs.io",
    "count": 188,
    "uniques": 21
  },
  {
    "referrer": "Google",
    "count": 116,
    "uniques": 15
  },
  {
    "referrer": "gradio-blocks-multilingual-aspect-based-sentimen-c04f821.hf.space",
    "count": 44,
    "uniques": 4
  },
  {
    "referrer": "yangheng-multilingual-aspect-based-sentiment-analysis.hf.space",
    "count": 36,
    "uniques": 4
  },
  {
    "referrer": "notebooks.githubusercontent.com",
    "count": 29,
    "uniques": 2
  },
  {
    "referrer": "colab.research.google.com",
    "count": 27,
    "uniques": 1
  },
  {
    "referrer": "pypi.org",
    "count": 23,
    "uniques": 3
  }
]