{
  "count": 976,
  "uniques": 126,
  "views": [
    {
      "timestamp": "2023-05-23T00:00:00Z",
      "count": 116,
      "uniques": 18
    },
    {
      "timestamp": "2023-05-24T00:00:00Z",
      "count": 135,
      "uniques": 20
    },
    {
      "timestamp": "2023-05-25T00:00:00Z",
      "count": 159,
      "uniques": 24
    },
    {
      "timestamp": "2023-05-26T00:00:00Z",
      "count": 149,
      "uniques": 16
    },
    {
      "timestamp": "2023-05-27T00:00:00Z",
      "count": 82,
      "uniques": 14
    },
    {
      "timestamp": "2023-05-28T00:00:00Z",
      "count": 157,
      "uniques": 17
    },
    {
      "timestamp": "2023-05-29T00:00:00Z",
      "count": 178,
      "uniques": 17
    }
  ]
}