[
  {
    "path": "/yangheng95/ABSADatasets",
    "title": "yangheng95/ABSADatasets: Public & Community-shared datasets for Aspect-based ...",
    "count": 284,
    "uniques": 129
  },
  {
    "path": "/yangheng95/ABSADatasets/tree/v2.0/datasets",
    "title": "ABSADatasets/datasets at v2.0 · yangheng95/ABSADatasets · GitHub",
    "count": 102,
    "uniques": 56
  },
  {
    "path": "/yangheng95/ABSADatasets/tree/v1.2/DPT",
    "title": "ABSADatasets/DPT at v1.2 · yangheng95/ABSADatasets · GitHub",
    "count": 96,
    "uniques": 38
  },
  {
    "path": "/yangheng95/ABSADatasets/tree/v2.0/datasets/atepc_datasets",
    "title": "GitHub - yangheng95/ABSADatasets: Public & Community-shared datasets for Aspe...",
    "count": 61,
    "uniques": 24
  },
  {
    "path": "/yangheng95/ABSADatasets/tree/v2.0/datasets/apc_datasets",
    "title": "ABSADatasets/datasets/apc_datasets at v2.0 · yangheng95/ABSADatasets · GitHub",
    "count": 56,
    "uniques": 33
  },
  {
    "path": "/yangheng95/ABSADatasets/tree/v1.2",
    "title": "yangheng95/ABSADatasets at v1.2",
    "count": 50,
    "uniques": 27
  },
  {
    "path": "/yangheng95/ABSADatasets/tree/v2.0/datasets/apc_datasets/100.CustomDataset",
    "title": "ABSADatasets/datasets/apc_datasets/100.CustomDataset at v2.0 · yangheng95/ABS...",
    "count": 25,
    "uniques": 12
  },
  {
    "path": "/yangheng95/ABSADatasets/tree/v2.0/datasets/atepc_datasets/110.SemEval",
    "title": "ABSADatasets/datasets/atepc_datasets/110.SemEval at v2.0 · yangheng95/ABSADat...",
    "count": 24,
    "uniques": 10
  },
  {
    "path": "/yangheng95/ABSADatasets/tree/v2.0/DPT",
    "title": "ABSADatasets/DPT at v2.0 · yangheng95/ABSADatasets · GitHub",
    "count": 22,
    "uniques": 13
  },
  {
    "path": "/yangheng95/ABSADatasets/tree/v1.2/datasets",
    "title": "ABSADatasets/datasets at v1.2 · yangheng95/ABSADatasets · GitHub",
    "count": 21,
    "uniques": 12
  }
]